tracer/__init__.py
tracer/tracefilter.py
tracer-2.0.0.dist-info/COPYING
tracer-2.0.0.dist-info/METADATA
tracer-2.0.0.dist-info/WHEEL
tracer-2.0.0.dist-info/top_level.txt
tracer-2.0.0.dist-info/RECORD
